LICENSE
MANIFEST.in
README.md
setup.cfg
setup.py
./ark/__init__.py
./ark/__main__.py
./ark/asyn.py
./ark/config.py
./ark/const.py
./ark/ctx.py
./ark/env.py
./ark/exc.py
./ark/lock.py
./ark/log.py
./ark/mock.py
./ark/patch.py
./ark/utils.py
./ark/apps/__init__.py
./ark/apps/consumer.py
./ark/apps/creator.py
./ark/apps/shell.py
./ark/apps/worker.py
./ark/apps/wsgi.py
./ark/apps/grpc/__init__.py
./ark/apps/grpc/grpc.py
./ark/apps/grpc/patch.py
./ark/bin/__init__.py
./ark/bin/ark.py
./ark/celery/__init__.py
./ark/celery/app.py
./ark/celery/config.py
./ark/celery/task.py
./ark/conf/__init__.py
./ark/conf/templates/commons/.coveragerc.jinja
./ark/conf/templates/commons/.flake8.jinja
./ark/conf/templates/commons/.pre-commit-config.yaml.jinja
./ark/conf/templates/commons/README.md.jinja
./ark/conf/templates/commons/infra.yaml.jinja
./ark/conf/templates/commons/infra_dev.yaml.jinja
./ark/conf/templates/commons/infra_ut.yaml.jinja
./ark/conf/templates/commons/protos/__init__.py.jinja
./ark/conf/templates/commons/protos/helloworld.proto.jinja
./ark/conf/templates/commons/protos/helloworld_pb2.py.jinja
./ark/conf/templates/commons/protos/helloworld_pb2_grpc.py.jinja
./ark/conf/templates/commons/protos/protoc.sh.jinja
./ark/conf/templates/v0/app.yaml.jinja
./ark/conf/templates/v0/{name}/__init__.py.jinja
./ark/conf/templates/v0/{name}/app.py.jinja
./ark/conf/templates/v0/{name}/clients.py.jinja
./ark/conf/templates/v0/{name}/consumer.py.jinja
./ark/conf/templates/v0/{name}/infras.py.jinja
./ark/conf/templates/v0/{name}/sender.py.jinja
./ark/conf/templates/v0/{name}/service.py.jinja
./ark/conf/templates/v1/app.yaml.jinja
./ark/conf/templates/v1/{name}/__init__.py.jinja
./ark/conf/templates/v1/{name}/app.py.jinja
./ark/conf/templates/v1/{name}/clients.py.jinja
./ark/conf/templates/v1/{name}/configs.py.jinja
./ark/conf/templates/v1/{name}/consts.py.jinja
./ark/conf/templates/v1/{name}/consumer.py.jinja
./ark/conf/templates/v1/{name}/exc.py.jinja
arkio.egg-info/PKG-INFO
arkio.egg-info/SOURCES.txt
arkio.egg-info/dependency_links.txt
arkio.egg-info/entry_points.txt
arkio.egg-info/not-zip-safe
arkio.egg-info/requires.txt
arkio.egg-info/top_level.txt