Metadata-Version: 2.1
Name: arkio
Version: 0.0.4
Summary: A backend microservice framework.
Home-page: https://github.com/arkio-run/arkio
Author: arkio.run
Author-email: arkio.run@icloud.com
License: UNKNOWN
Project-URL: Documentation, https://github.com/arkio-run/arkio/wiki
Project-URL: Issue Tracker, https://github.com/arkio-run/arkio/issues
Keywords: grpc
Platform: UNKNOWN
Classifier: Development Status :: 5 - Production/Stable
Classifier: Intended Audience :: Developers
Classifier: Programming Language :: Python
Classifier: Programming Language :: Python :: 3
Requires-Python: >=3.6
License-File: LICENSE
